[
    {
        "id": 3238040,
        "route": [
            "p0",
            "p2",
            "d2",
            "d0"
        ],
        "location": [
            0,
            13,
            17,
            0
        ]
    },
    {
        "id": 3238028,
        "route": [
            "p0",
            "p1",
            "d1",
            "p3",
            "d3",
            "d0"
        ],
        "location": [
            0,
            1,
            17,
            13,
            17,
            0
        ]
    }
]